odoo/addons/stock_picking_customer_ref/README.rst
odoo/addons/stock_picking_customer_ref/__init__.py
odoo/addons/stock_picking_customer_ref/__manifest__.py
odoo/addons/stock_picking_customer_ref/i18n/de.po
odoo/addons/stock_picking_customer_ref/i18n/es.po
odoo/addons/stock_picking_customer_ref/i18n/fr.po
odoo/addons/stock_picking_customer_ref/i18n/hr.po
odoo/addons/stock_picking_customer_ref/i18n/it.po
odoo/addons/stock_picking_customer_ref/i18n/nl.po
odoo/addons/stock_picking_customer_ref/i18n/pt.po
odoo/addons/stock_picking_customer_ref/i18n/pt_BR.po
odoo/addons/stock_picking_customer_ref/i18n/sl_SI.po
odoo/addons/stock_picking_customer_ref/i18n/stock_picking_customer_ref.pot
odoo/addons/stock_picking_customer_ref/models/__init__.py
odoo/addons/stock_picking_customer_ref/models/stock_picking.py
odoo/addons/stock_picking_customer_ref/readme/CONTRIBUTORS.rst
odoo/addons/stock_picking_customer_ref/readme/CREDITS.rst
odoo/addons/stock_picking_customer_ref/readme/DESCRIPTION.rst
odoo/addons/stock_picking_customer_ref/readme/USAGE.rst
odoo/addons/stock_picking_customer_ref/static/description/icon.png
odoo/addons/stock_picking_customer_ref/static/description/index.html
odoo/addons/stock_picking_customer_ref/tests/__init__.py
odoo/addons/stock_picking_customer_ref/tests/test_stock_picking_customer_ref.py
odoo/addons/stock_picking_customer_ref/views/stock_picking_view.xml
odoo13_addon_stock_picking_customer_ref-13.0.1.0.1.dev5.dist-info/METADATA
odoo13_addon_stock_picking_customer_ref-13.0.1.0.1.dev5.dist-info/WHEEL
odoo13_addon_stock_picking_customer_ref-13.0.1.0.1.dev5.dist-info/top_level.txt
odoo13_addon_stock_picking_customer_ref-13.0.1.0.1.dev5.dist-info/RECORD
